{
    "province"            :    "PROVINSI JAWA BARAT",
    "regencyCity"         :    "KOTA BOGOR",
    "issued"              :    "BOGOR KOTA 05-02-201",
    "nik"                 :    "3271051609670001",
    "name"                :    "DRS. ACHMAD BARLIAN, MM.",
    "gender"              :    "LAKI-LAKI",
    "placeAndDateOfBirth" :   "BANDUNG, 6-09-1967",
    "bloodType"           :    "O",
    "rtRw"                :    "003/016",
    "address"             :    "",
    "village"             :    "TEGALGUNDIL",
    "district"            :    "BOGOR UTARA",
    "religion"            :    "",
    "marital"             :    "",
    "nationality"         :    "",
    "job"                 :    "RYAWAN BUMN",
    "validUntil"          :    "16-09-2018"
}

